napari_hdf5_labels_io/__init__.py
napari_hdf5_labels_io/_reader.py
napari_hdf5_labels_io/_writer.py
napari_hdf5_labels_io/_tests/__init__.py
napari_hdf5_labels_io/_tests/test_reader.py
napari_hdf5_labels_io/_tests/test_writer.py
napari_hdf5_labels_io-0.3.dev16.dist-info/LICENSE
napari_hdf5_labels_io-0.3.dev16.dist-info/METADATA
napari_hdf5_labels_io-0.3.dev16.dist-info/WHEEL
napari_hdf5_labels_io-0.3.dev16.dist-info/entry_points.txt
napari_hdf5_labels_io-0.3.dev16.dist-info/top_level.txt
napari_hdf5_labels_io-0.3.dev16.dist-info/RECORD
