Metadata-Version: 2.1
Name: napari-hdf5-labels-io
Version: 0.3.dev16
Summary: Napari plugin to store set of layers in a .h5 file. Label layer are stored in a sparse representation.
Home-page: https://github.com/yapic/napari-hdf5-labels-io
Author: Duway Nicolas Lesmes Leon, Pranjal Dhole
Author-email: dlesmesleon@hotmail.com, dhole.pranjal@gmail.com
License: GNU GPL v3.0
Platform: UNKNOWN
Classifier: Development Status :: 4 - Beta
Classifier: Intended Audience :: Developers
Classifier: Framework :: napari
Classifier: Topic :: Software Development :: Testing
Classifier: Programming Language :: Python
Classifier: Programming Language :: Python :: 3
Classifier: Programming Language :: Python :: 3.7
Classifier: Programming Language :: Python :: 3.8
Classifier: Operating System :: OS Independent
Classifier: License :: OSI Approved :: GNU General Public License v3 (GPLv3)
Requires-Python: <3.9
License-File: LICENSE
Requires-Dist: napari-plugin-engine (>=0.1.4)
Requires-Dist: typing
Requires-Dist: numpy
Requires-Dist: sparse
Requires-Dist: h5py (==2.10.0)
Requires-Dist: zarr
